CUmodules/__init__.py
CUmodules/colors_ugen.py
colorsugen/__init__.py
colorsugen/colorsugen.py
colorsugen-0.0.12.data/data/share/colorsugen/doc/LICENSE
colorsugen-0.0.12.data/data/share/colorsugen/doc/README.md
colorsugen-0.0.12.data/scripts/color-pal
colorsugen-0.0.12.dist-info/LICENSE
colorsugen-0.0.12.dist-info/METADATA
colorsugen-0.0.12.dist-info/WHEEL
colorsugen-0.0.12.dist-info/top_level.txt
colorsugen-0.0.12.dist-info/RECORD
